paulicirq/__init__.py
paulicirq/_version.py
paulicirq/grad.py
paulicirq/linear_combinations.py
paulicirq/op_tree.py
paulicirq/pauli.py
paulicirq/algorithms/__init__.py
paulicirq/algorithms/pauliword.py
paulicirq/algorithms/qubit_reduce.py
paulicirq/gates/__init__.py
paulicirq/gates/controlled_gates.py
paulicirq/gates/gate_block.py
paulicirq/gates/general_rotation.py
paulicirq/gates/hadamard_test_gate.py
paulicirq/gates/overlap_test_gate.py
paulicirq/gates/pauli_exp_gates.py
paulicirq/gates/random_gates.py
paulicirq/gates/swap_test_gate.py
paulicirq/gates/universal_gate_set.py
paulicirq/layers/__init__.py
paulicirq/layers/addpqc.py
paulicirq/layers/swaptest.py
paulicirq/utils/__init__.py
paulicirq/utils/_cirq.py
paulicirq/utils/_numpy.py
paulicirq/utils/_python.py
paulicirq/utils/_tf.py
paulicirq-0.1.0.dist-info/LICENSE
paulicirq-0.1.0.dist-info/METADATA
paulicirq-0.1.0.dist-info/WHEEL
paulicirq-0.1.0.dist-info/top_level.txt
paulicirq-0.1.0.dist-info/RECORD
