Metadata-Version: 2.1
Name: paulicirq
Version: 0.1.0
Home-page: https://github.com/Psrit/paulicirq
Author: xiaojx
Author-email: xiaojx13@outlook.com
Classifier: Environment :: Console
Classifier: Intended Audience :: Developers
Classifier: Intended Audience :: Education
Classifier: Operating System :: Unix
Classifier: Programming Language :: Python :: 3.8
Classifier: Topic :: Software Development :: Libraries :: Python Modules
License-File: LICENSE
Requires-Dist: cirq-core (==0.13.1)
Requires-Dist: cirq-google (==0.13.1)
Requires-Dist: sympy (==1.8)
Requires-Dist: numpy (==1.19.5)
Requires-Dist: nbformat (==5.9.2)
Requires-Dist: pylint (==2.4.4)
Requires-Dist: yapf (==0.28.0)
Requires-Dist: tensorflow (==2.7.0)
Requires-Dist: tensorflow-quantum (==0.7.2)
Requires-Dist: googleapis-common-protos (==1.52.0)
Requires-Dist: google-api-core (==1.21.0)
Requires-Dist: google-auth (==1.18.0)
Requires-Dist: google-api-python-client (==1.8.0)
Requires-Dist: grpcio (==1.34.1)
Requires-Dist: protobuf (==3.17.3)
Requires-Dist: ddt
Requires-Dist: openfermion (==1.4.0)
